dagen/__init__.py
dagen/_version.py
dagen/image/__init__.py
dagen/image/image.py
dagen-0.1.4.dist-info/DESCRIPTION.rst
dagen-0.1.4.dist-info/METADATA
dagen-0.1.4.dist-info/RECORD
dagen-0.1.4.dist-info/WHEEL
dagen-0.1.4.dist-info/metadata.json
dagen-0.1.4.dist-info/top_level.txt
