Metadata-Version: 2.0
Name: dagen
Version: 0.1.4
Summary: syntetic data generation for deep learning experiments
Home-page: https://github.com/undertherain/dagen
Author: UNKNOWN
Author-email: UNKNOWN
License: UNKNOWN
Keywords: deep learning,dataset,generation
Platform: UNKNOWN
Classifier: Development Status :: 2 - Pre-Alpha
Classifier: Environment :: Console
Classifier: License :: OSI Approved :: Apache Software License
Classifier: Natural Language :: English
Classifier: Operating System :: POSIX
Classifier: Programming Language :: Python :: 3.4
Classifier: Programming Language :: Python :: 3.5
Classifier: Programming Language :: Python :: 3.6
Classifier: Programming Language :: Python :: 3 :: Only
Requires-Dist: numpy
Requires-Dist: pillow
Requires-Dist: contextfree
